wafw00f/__init__.py
wafw00f/main.py
wafw00f/manager.py
wafw00f/wafprio.py
wafw00f/bin/wafw00f
wafw00f/lib/__init__.py
wafw00f/lib/asciiarts.py
wafw00f/lib/evillib.py
wafw00f/plugins/__init__.py
wafw00f/plugins/aesecure.py
wafw00f/plugins/airee.py
wafw00f/plugins/airlock.py
wafw00f/plugins/alertlogic.py
wafw00f/plugins/aliyundun.py
wafw00f/plugins/anquanbao.py
wafw00f/plugins/anubis.py
wafw00f/plugins/anyu.py
wafw00f/plugins/applicationgateway.py
wafw00f/plugins/approach.py
wafw00f/plugins/armor.py
wafw00f/plugins/arvancloud.py
wafw00f/plugins/aspa.py
wafw00f/plugins/aspnetgen.py
wafw00f/plugins/astra.py
wafw00f/plugins/awswaf.py
wafw00f/plugins/azion.py
wafw00f/plugins/baffinbay.py
wafw00f/plugins/baidu.py
wafw00f/plugins/barikode.py
wafw00f/plugins/barracuda.py
wafw00f/plugins/bekchy.py
wafw00f/plugins/beluga.py
wafw00f/plugins/binarysec.py
wafw00f/plugins/bitninja.py
wafw00f/plugins/blockdos.py
wafw00f/plugins/bluedon.py
wafw00f/plugins/bulletproof.py
wafw00f/plugins/cachefly.py
wafw00f/plugins/cachewall.py
wafw00f/plugins/cdnns.py
wafw00f/plugins/cerber.py
wafw00f/plugins/chinacache.py
wafw00f/plugins/chuangyu.py
wafw00f/plugins/ciscoacexml.py
wafw00f/plugins/cloudbric.py
wafw00f/plugins/cloudflare.py
wafw00f/plugins/cloudfloordns.py
wafw00f/plugins/cloudfront.py
wafw00f/plugins/cloudprotector.py
wafw00f/plugins/comodo.py
wafw00f/plugins/crawlprotect.py
wafw00f/plugins/ddosguard.py
wafw00f/plugins/denyall.py
wafw00f/plugins/distil.py
wafw00f/plugins/dosarrest.py
wafw00f/plugins/dotdefender.py
wafw00f/plugins/dynamicweb.py
wafw00f/plugins/edgecast.py
wafw00f/plugins/eisoo.py
wafw00f/plugins/envoy.py
wafw00f/plugins/expressionengine.py
wafw00f/plugins/f5bigipapm.py
wafw00f/plugins/f5bigipasm.py
wafw00f/plugins/f5bigipltm.py
wafw00f/plugins/f5firepass.py
wafw00f/plugins/f5trafficshield.py
wafw00f/plugins/fastly.py
wafw00f/plugins/fortigate.py
wafw00f/plugins/fortiguard.py
wafw00f/plugins/fortiweb.py
wafw00f/plugins/frontdoor.py
wafw00f/plugins/gcparmor.py
wafw00f-2.4.2.dist-info/licenses/LICENSE
wafw00f-2.4.2.dist-info/METADATA
wafw00f-2.4.2.dist-info/WHEEL
wafw00f-2.4.2.dist-info/entry_points.txt
wafw00f-2.4.2.dist-info/top_level.txt
wafw00f-2.4.2.dist-info/RECORD
