Metadata-Version: 2.4
Name: wafw00f
Version: 2.4.2
Summary: The Web Application Firewall Fingerprinting Toolkit
Author-email: Sandro Gauci <sandro@enablesecurity.com>
License-Expression: BSD-3-Clause
Project-URL: Homepage, https://github.com/enablesecurity/wafw00f
Project-URL: Bug Tracker, https://github.com/EnableSecurity/wafw00f/issues
Project-URL: Documentation, https://github.com/EnableSecurity/wafw00f/wiki
Project-URL: Source Code, https://github.com/EnableSecurity/wafw00f/tree/master
Keywords: waf,firewall,detector,fingerprint
Classifier: Development Status :: 5 - Production/Stable
Classifier: Intended Audience :: System Administrators
Classifier: Intended Audience :: Information Technology
Classifier: Topic :: Internet
Classifier: Topic :: Security
Classifier: Topic :: System :: Networking :: Firewalls
Classifier: Programming Language :: Python :: 3
Classifier: Operating System :: OS Independent
Requires-Python: >=3.10
License-File: LICENSE
Requires-Dist: requests
Requires-Dist: requests[socks]
Provides-Extra: dev
Requires-Dist: prospector; extra == "dev"
Requires-Dist: pytest; extra == "dev"
Requires-Dist: pytest-mock; extra == "dev"
Requires-Dist: responses; extra == "dev"
Provides-Extra: docs
Requires-Dist: Sphinx; extra == "docs"
Dynamic: license-file
